{
  "document_scores": {
    "0": [
      4
    ],
    "229": [
      4
    ],
    "227": [
      4
    ]
  },
  "query_history": [
    {
      "id": "query_0",
      "question": "What is Artificial Intelligence?",
      "answer": "Com base nos documentos encontrados sobre 'What is Artificial Intelligence?':\n\nDe 'Artificial intelligence': Artificial intelligence (AI) is the capability of computational systems to perform tasks typically associated with human intelligence, such as learning, reasoning, problem-solving, perception, and decision-making. It is a field of research in computer science that develops and studies methods and so\n\nDe 'Artificial intelligence': \"intelligence\" of the machine—and no other philosophical discussion is required, or may not even be possible.\n\nAnother definition has been adopted by Google, a major practitioner in the field of AI. This definition stipulates the ability of systems to synthesize information as the manifestation of i\n\nDe 'Artificial intelligence': intelligence is not, by definition, simulation of human intelligence\".\n\nMcCarthy defines intelligence as \"...",
      "rating": 4,
      "timestamp": "2025-07-22T10:47:50.047806",
      "docs_used": [
        {
          "chunk_id": 0,
          "title": "Artificial intelligence",
          "weight": 1.0,
          "confidence": "Médio"
        },
        {
          "chunk_id": 229,
          "title": "Artificial intelligence",
          "weight": 1.0,
          "confidence": "Médio"
        },
        {
          "chunk_id": 227,
          "title": "Artificial intelligence",
          "weight": 1.0,
          "confidence": "Médio"
        }
      ]
    }
  ],
  "session_data": [
    {
      "id": "query_0",
      "question": "What is Artificial Intelligence?",
      "answer": "Com base nos documentos encontrados sobre 'What is Artificial Intelligence?':\n\nDe 'Artificial intelligence': Artificial intelligence (AI) is the capability of computational systems to perform tasks typically associated with human intelligence, such as learning, reasoning, problem-solving, perception, and decision-making. It is a field of research in computer science that develops and studies methods and so\n\nDe 'Artificial intelligence': \"intelligence\" of the machine—and no other philosophical discussion is required, or may not even be possible.\n\nAnother definition has been adopted by Google, a major practitioner in the field of AI. This definition stipulates the ability of systems to synthesize information as the manifestation of i\n\nDe 'Artificial intelligence': intelligence is not, by definition, simulation of human intelligence\".\n\nMcCarthy defines intelligence as \"...",
      "rating": 4,
      "timestamp": "2025-07-22T10:47:50.047806",
      "docs_used": [
        {
          "chunk_id": 0,
          "title": "Artificial intelligence",
          "weight": 1.0,
          "confidence": "Médio"
        },
        {
          "chunk_id": 229,
          "title": "Artificial intelligence",
          "weight": 1.0,
          "confidence": "Médio"
        },
        {
          "chunk_id": 227,
          "title": "Artificial intelligence",
          "weight": 1.0,
          "confidence": "Médio"
        }
      ]
    }
  ],
  "stats": {
    "total_queries": 1,
    "total_documents_with_feedback": 3,
    "last_updated": "2025-07-22T10:47:50.056580",
    "version": "2.0_super_robust"
  },
  "metadata": {
    "created_at": "2025-07-22T10:47:50.056818",
    "system_type": "super_robust_rag"
  }
}